st_mongo_connection/__init__.py
st_mongo_connection/mongo.py
st_mongo_connection-1.0.2.dist-info/METADATA
st_mongo_connection-1.0.2.dist-info/WHEEL
st_mongo_connection-1.0.2.dist-info/licenses/LICENSE
st_mongo_connection-1.0.2.dist-info/RECORD
