Metadata-Version: 2.1
Name: st-mongo-connection
Version: 1.0.2
Summary: Streamlit MongoDB Connector: An efficient connector for interfacing MongoDB with Streamlit apps
Project-URL: Homepage, https://github.com/Mortafix/streamlit-mongo
Project-URL: Issues, https://github.com/Mortafix/streamlit-mongo/issues
Author-email: Moris Doratiotto <me@moris.dev>
License: 
License-File: LICENSE
Keywords: database,mongo,streamlit
Classifier: Development Status :: 4 - Beta
Classifier: Intended Audience :: Developers
Classifier: License :: OSI Approved :: MIT License
Classifier: Operating System :: OS Independent
Classifier: Programming Language :: Python :: 3
Requires-Python: >=3.9
Requires-Dist: pymongo>=4.6.0
Requires-Dist: streamlit>=1.29.0
